Metadata-Version: 1.0
Name: ever2text
Version: 0.2
Summary: Convert Evernote exports to text files
Home-page: http://nicholaskuechler.com
Author: Nicholas Kuechler
Author-email: nicholaskuechler@nicholaskuechler.com
License: UNKNOWN
Keywords: note taking migration
Platform: UNKNOWN
